webhdfs_py/__init__.py
webhdfs_py/errors.py
webhdfs_py/operations.py
webhdfs_py/webhdfs.py
webhdfs_py/example/README.py
webhdfs_py/example/__init__.py
webhdfs_py/example/run.py
webhdfs_py/example/utils.py
webhdfs_py/example/pages/main.py
webhdfs_py_client-0.2.dist-info/METADATA
webhdfs_py_client-0.2.dist-info/WHEEL
webhdfs_py_client-0.2.dist-info/top_level.txt
webhdfs_py_client-0.2.dist-info/RECORD
