Metadata-Version: 2.1
Name: webhdfs-py-client
Version: 0.2
Summary: Python wrapper for the Hadoop WebHDFS REST API
Home-page: 
Author: Erik Alejandro Abdala
Author-email: e.ale.abdala@gmail.com
Classifier: Intended Audience :: Information Technology
Classifier: Intended Audience :: Developers
Classifier: License :: OSI Approved :: Apache Software License
Classifier: Operating System :: POSIX :: Linux
Classifier: Programming Language :: Python
Classifier: Programming Language :: Python :: 2
Classifier: Programming Language :: Python :: 2.7
Classifier: Programming Language :: Python :: 3.4
Classifier: Programming Language :: Python :: 3.9
Requires-Python: >=3.7, <=3.10
Requires-Dist: requests
Requires-Dist: six
Requires-Dist: streamlit
Requires-Dist: tqdm
